[{"file_name": "1_2010-11-26.jpg", "size": "z"}, {"file_name": "1_2010-11-14.jpg", "size": "x"}, {"file_name": "1_2011-01-05.jpg", "size": "z"}, {"file_name": "9.jpg", "size": "z"}, {"file_name": "15_2011-07-03.jpg", "size": "z"}, {"file_name": "3_2011-08-09.jpg", "size": "z"}, {"file_name": "3_2011-08-16.jpg", "size": "z"}, {"file_name": "14_2011-11-16.jpg", "size": "z"}, {"file_name": "26_2011-11-20.jpg", "size": "z"}, {"file_name": "11.jpg", "size": "z"}, {"file_name": "36_2012-07-15.jpg", "size": "y"}, {"file_name": "13.jpg", "size": "z"}, {"file_name": "8.jpg", "size": "z"}, {"file_name": "17_2013-05-20.jpg", "size": "y"}, {"file_name": "14_2013-07-18.jpg", "size": "z"}, {"file_name": "12_2013-09-03.jpg", "size": "z"}, {"file_name": "12_2013-12-14.jpg", "size": "z"}, {"file_name": "10.jpg", "size": "x"}, {"file_name": "15_2013-12-30.jpg", "size": "z"}, {"file_name": "17_2014-01-04.jpg", "size": "z"}, {"file_name": "18.jpg", "size": "z"}, {"file_name": "24.jpg", "size": "z"}, {"file_name": "26_2015-02-22.jpg", "size": "z"}, {"file_name": "27.jpg", "size": "z"}, {"file_name": "25.jpg", "size": "z"}, {"file_name": "40.jpg", "size": "z"}, {"file_name": "36_2017-03-02.jpg", "size": "z"}, {"file_name": "47.jpg", "size": "z"}, {"file_name": "86.jpg", "size": "z"}, {"file_name": "45.jpg", "size": "z"}, {"file_name": "61.jpg", "size": "z"}]